Metadata-Version: 2.4
Name: nbitk
Version: 0.7.3
Summary: Naturalis Biodiversity Informatics ToolKit
Author-email: Pierre-Etienne Cholley <pierreetienne.cholley@naturalis.nl>, Ward Gielis <ward.gielis@naturalis.nl>, Dick Groenenberg <dick.groenenberg@naturalis.nl>, Edwin den Haas <edwin.denhaas@naturalis.nl>, Dominika Kresa <dominika.kresa@naturalis.nl>, Luka Lenaroto <luka.lenaroto@naturalis.nl>, Luuk Nolden <luuk.nolden@naturalis.nl>, Rutger Vos <rutger.vos@naturalis.nl>
License:                                  Apache License
Requires-Python: >=3.12
License-File: LICENSE
Requires-Dist: biopython
Requires-Dist: pandas
Requires-Dist: openpyxl
Requires-Dist: requests
Requires-Dist: minio
Requires-Dist: pyyaml
Requires-Dist: bioblend
Requires-Dist: tqdm
Dynamic: license-file
